uvolution/__init__.py
uvolution/session/__init__.py
uvolution/session/base.py
uvolution/ulogger/__init__.py
uvolution/ulogger/handlers.py
uvolution/utils/colors.py
uvolution/utils/exceptions.py
uvolution/utils/executor.py
uvolution-0.1.0.dist-info/METADATA
uvolution-0.1.0.dist-info/WHEEL
uvolution-0.1.0.dist-info/entry_points.txt
uvolution-0.1.0.dist-info/licenses/LICENSE
uvolution-0.1.0.dist-info/RECORD
