Metadata-Version: 2.4
Name: uvolution
Version: 0.1.0
Summary: Add your description here
Author-email: Alexeev Bronislav <alexeev.dev@mail.ru>
License-File: LICENSE
Requires-Python: >=3.13
Requires-Dist: click>=8.1.8
Requires-Dist: rich>=13.9.4
